photovoltaic_modeling/command_line.py
photovoltaic_modeling/parameter_extraction.py
photovoltaic_modeling/version.py
photovoltaic_modeling/diode_model/multiple_modules_single_diode_model.py
photovoltaic_modeling/diode_model/report_helper.py
photovoltaic_modeling/diode_model/single_diode_model.py
photovoltaic_modeling/diode_model/single_voltage_irradiance_dependence.py
photovoltaic_modeling/examples/parameter_extraction_execution.py
photovoltaic_modeling/examples/diode_model/single_diode_model/rng-100d_one_module_no_shading.py
photovoltaic_modeling/examples/parameter/parameter_extraction_execution.py
photovoltaic_modeling/parameter/parameter_extraction.py
photovoltaic_modeling_python-0.2.1.dist-info/DESCRIPTION.rst
photovoltaic_modeling_python-0.2.1.dist-info/METADATA
photovoltaic_modeling_python-0.2.1.dist-info/RECORD
photovoltaic_modeling_python-0.2.1.dist-info/WHEEL
photovoltaic_modeling_python-0.2.1.dist-info/entry_points.txt
photovoltaic_modeling_python-0.2.1.dist-info/metadata.json
photovoltaic_modeling_python-0.2.1.dist-info/top_level.txt
tests/photovoltaic_modeling/test_parameter_extraction.py
tests/photovoltaic_modeling/diode_model/test_multiple_modules_single_diode_model.py
tests/photovoltaic_modeling/diode_model/test_single_diode_model.py
tests/photovoltaic_modeling/diode_model/test_single_voltage_irradiance_dependence.py
tests/photovoltaic_modeling/parameter/test_parameter_extraction.py
