Metadata-Version: 2.0
Name: photovoltaic-modeling-python
Version: 0.2.1
Summary: Get the parameters that are not available in the datasheet of photovoltaic modules and get I-V and P-V curves.
Home-page: https://github.com/tadatoshi/photovoltaic_modeling_python
Author: Tadatoshi Takahashi
Author-email: tadatoshi@gmail.com
License: MIT
Keywords: control optimization engineering
Platform: UNKNOWN
Classifier: Development Status :: 3 - Alpha
Classifier: Intended Audience :: Developers
Classifier: Topic :: Scientific/Engineering
Classifier: License :: OSI Approved :: MIT License
Classifier: Programming Language :: Python :: 3.4
Classifier: Programming Language :: Python :: 3.5
Requires-Dist: matplotlib
Requires-Dist: numpy
Requires-Dist: scipy
